odoo/addons/stock_release_channel_auto_release/README.rst
odoo/addons/stock_release_channel_auto_release/__init__.py
odoo/addons/stock_release_channel_auto_release/__manifest__.py
odoo/addons/stock_release_channel_auto_release/i18n/es.po
odoo/addons/stock_release_channel_auto_release/i18n/fr.po
odoo/addons/stock_release_channel_auto_release/i18n/it.po
odoo/addons/stock_release_channel_auto_release/i18n/stock_release_channel_auto_release.pot
odoo/addons/stock_release_channel_auto_release/models/__init__.py
odoo/addons/stock_release_channel_auto_release/models/stock_picking.py
odoo/addons/stock_release_channel_auto_release/models/stock_release_channel.py
odoo/addons/stock_release_channel_auto_release/readme/CONTRIBUTORS.md
odoo/addons/stock_release_channel_auto_release/readme/DESCRIPTION.md
odoo/addons/stock_release_channel_auto_release/readme/USAGE.md
odoo/addons/stock_release_channel_auto_release/static/description/icon.png
odoo/addons/stock_release_channel_auto_release/static/description/index.html
odoo/addons/stock_release_channel_auto_release/tests/__init__.py
odoo/addons/stock_release_channel_auto_release/tests/test_channel_release_auto.py
odoo/addons/stock_release_channel_auto_release/views/stock_release_channel.xml
odoo_addon_stock_release_channel_auto_release-18.0.1.0.0.2.dist-info/METADATA
odoo_addon_stock_release_channel_auto_release-18.0.1.0.0.2.dist-info/WHEEL
odoo_addon_stock_release_channel_auto_release-18.0.1.0.0.2.dist-info/top_level.txt
odoo_addon_stock_release_channel_auto_release-18.0.1.0.0.2.dist-info/RECORD
